{
  "campaign_metadata": {
    "N": "41",
    "campaign_duration": "10 (days remaining only)",
    "target_dana": "Rp3.000.000.000"
  },
  "total_donors_scraped": 41,
  "donors": [
    {
      "name": "Orang Baik",
      "amount": "Rp1.000",
      "time_ago": "4 bulan yang lalu"
    },
    {
      "name": "Orang Baik",
      "amount": "Rp1.000",
      "time_ago": "6 bulan yang lalu"
    },
    {
      "name": "Orang Baik",
      "amount": "Rp5.000",
      "time_ago": "7 bulan yang lalu"
    },
    {
      "name": "Orang Baik",
      "amount": "Rp1.000",
      "time_ago": "setahun yang lalu"
    },
    {
      "name": "Orang Baik",
      "amount": "Rp1.000",
      "time_ago": "setahun yang lalu"
    },
    {
      "name": "Orang Baik",
      "amount": "Rp1.000",
      "time_ago": "setahun yang lalu"
    },
    {
      "name": "Orang Baik",
      "amount": "Rp5.000",
      "time_ago": "setahun yang lalu"
    },
    {
      "name": "Zumrotun Taqiyah",
      "amount": "Rp1.000",
      "time_ago": "setahun yang lalu"
    },
    {
      "name": "Orang Baik",
      "amount": "Rp5.000",
      "time_ago": "setahun yang lalu"
    },
    {
      "name": "ab",
      "amount": "Rp1.000",
      "time_ago": "setahun yang lalu"
    },
    {
      "name": "Orang Baik",
      "amount": "Rp15.000",
      "time_ago": "setahun yang lalu"
    },
    {
      "name": "Orang Baik",
      "amount": "Rp20.000",
      "time_ago": "setahun yang lalu"
    },
    {
      "name": "Orang Baik",
      "amount": "Rp1.000",
      "time_ago": "setahun yang lalu"
    },
    {
      "name": "Orang Baik",
      "amount": "Rp1.000",
      "time_ago": "setahun yang lalu"
    },
    {
      "name": "Orang Baik",
      "amount": "Rp50.000",
      "time_ago": "setahun yang lalu"
    },
    {
      "name": "Taufiqur Rohman",
      "amount": "Rp1.000",
      "time_ago": "2 tahun yang lalu"
    },
    {
      "name": "Orang Baik",
      "amount": "Rp1.000",
      "time_ago": "2 tahun yang lalu"
    },
    {
      "name": "Taufiqur Rohman",
      "amount": "Rp1.000",
      "time_ago": "2 tahun yang lalu"
    },
    {
      "name": "Syeikhul Alim",
      "amount": "Rp20.318",
      "time_ago": "2 tahun yang lalu"
    },
    {
      "name": "Orang Baik",
      "amount": "Rp3.000",
      "time_ago": "2 tahun yang lalu"
    },
    {
      "name": "Orang Baik",
      "amount": "Rp1.000",
      "time_ago": "2 tahun yang lalu"
    },
    {
      "name": "Orang Baik",
      "amount": "Rp100.000",
      "time_ago": "2 tahun yang lalu"
    },
    {
      "name": "Orang Baik",
      "amount": "Rp3.000",
      "time_ago": "2 tahun yang lalu"
    },
    {
      "name": "Orang Baik",
      "amount": "Rp2.000",
      "time_ago": "2 tahun yang lalu"
    },
    {
      "name": "Orang Baik",
      "amount": "Rp100.000",
      "time_ago": "2 tahun yang lalu"
    },
    {
      "name": "febry",
      "amount": "Rp5.000",
      "time_ago": "2 tahun yang lalu"
    },
    {
      "name": "Orang Baik",
      "amount": "Rp5.000",
      "time_ago": "2 tahun yang lalu"
    },
    {
      "name": "Orang Baik",
      "amount": "Rp10.000",
      "time_ago": "2 tahun yang lalu"
    },
    {
      "name": "Orang Baik",
      "amount": "Rp10.000",
      "time_ago": "2 tahun yang lalu"
    },
    {
      "name": "Orang Baik",
      "amount": "Rp150.000",
      "time_ago": "2 tahun yang lalu"
    },
    {
      "name": "Orang Baik",
      "amount": "Rp10.000",
      "time_ago": "2 tahun yang lalu"
    },
    {
      "name": "Orang Baik",
      "amount": "Rp3.000",
      "time_ago": "2 tahun yang lalu"
    },
    {
      "name": "Orang Baik",
      "amount": "Rp2.000",
      "time_ago": "2 tahun yang lalu"
    },
    {
      "name": "Alvina utami putri",
      "amount": "Rp15.000",
      "time_ago": "2 tahun yang lalu"
    },
    {
      "name": "Orang Baik",
      "amount": "Rp1.000",
      "time_ago": "2 tahun yang lalu"
    },
    {
      "name": "Orang Baik",
      "amount": "Rp5.000",
      "time_ago": "2 tahun yang lalu"
    },
    {
      "name": "Taufiqur Rohman",
      "amount": "Rp1.000",
      "time_ago": "2 tahun yang lalu"
    },
    {
      "name": "Orang Baik",
      "amount": "Rp5.000",
      "time_ago": "2 tahun yang lalu"
    },
    {
      "name": "Orang Baik",
      "amount": "Rp1.000",
      "time_ago": "2 tahun yang lalu"
    },
    {
      "name": "Tya Octavian",
      "amount": "Rp5.000",
      "time_ago": "2 tahun yang lalu"
    },
    {
      "name": "Orang Baik",
      "amount": "Rp3.000",
      "time_ago": "2 tahun yang lalu"
    }
  ]
}